dsetool/policy/__init__.py
dsetool/policy/configure.zcml
dsetool/policy/interfaces.py
dsetool/policy/setuphandlers.py
dsetool/policy/testing.py
dsetool/policy/adapters/__init__.py
dsetool/policy/adapters/configure.zcml
dsetool/policy/adapters/traversing.py
dsetool/policy/browser/configure.zcml
dsetool/policy/browser/list_questions.py
dsetool/policy/browser/webhelpers.py
dsetool/policy/browser/overrides/euphorie.client.browser.templates.login.pt
dsetool/policy/browser/templates/identification.pt
dsetool/policy/browser/templates/list_questions.pt
dsetool/policy/browser/templates/start.pt
dsetool/policy/locales/euphorie.pot
dsetool/policy/locales/bg/LC_MESSAGES/euphorie.po
dsetool/policy/locales/ca/LC_MESSAGES/euphorie.po
dsetool/policy/locales/cs/LC_MESSAGES/euphorie.po
dsetool/policy/locales/da/LC_MESSAGES/euphorie.po
dsetool/policy/locales/de/LC_MESSAGES/euphorie.po
dsetool/policy/locales/el/LC_MESSAGES/euphorie.po
dsetool/policy/locales/en/LC_MESSAGES/euphorie.po
dsetool/policy/locales/es/LC_MESSAGES/euphorie.po
dsetool/policy/locales/et/LC_MESSAGES/euphorie.po
dsetool/policy/locales/fi/LC_MESSAGES/euphorie.po
dsetool/policy/locales/fr/LC_MESSAGES/euphorie.po
dsetool/policy/locales/hr/LC_MESSAGES/euphorie.po
dsetool/policy/locales/hu/LC_MESSAGES/euphorie.po
dsetool/policy/locales/is/LC_MESSAGES/euphorie.po
dsetool/policy/locales/it/LC_MESSAGES/euphorie.po
dsetool/policy/locales/lt/LC_MESSAGES/euphorie.po
dsetool/policy/locales/lv/LC_MESSAGES/euphorie.po
dsetool/policy/locales/mt/LC_MESSAGES/euphorie.po
dsetool/policy/locales/nl/LC_MESSAGES/euphorie.po
dsetool/policy/locales/nl_BE/LC_MESSAGES/euphorie.po
dsetool/policy/locales/no/LC_MESSAGES/euphorie.po
dsetool/policy/locales/pl/LC_MESSAGES/euphorie.po
dsetool/policy/locales/pt/LC_MESSAGES/euphorie.po
dsetool/policy/locales/ro/LC_MESSAGES/euphorie.po
dsetool/policy/locales/sk/LC_MESSAGES/euphorie.po
dsetool/policy/locales/sl/LC_MESSAGES/euphorie.po
dsetool/policy/locales/sv/LC_MESSAGES/euphorie.po
dsetool_policy-1.0.3.dist-info/METADATA
dsetool_policy-1.0.3.dist-info/WHEEL
dsetool_policy-1.0.3.dist-info/entry_points.txt
dsetool_policy-1.0.3.dist-info/top_level.txt
dsetool_policy-1.0.3.dist-info/RECORD
