Metadata-Version: 2.4
Name: dsetool.policy
Version: 1.0.3
Summary: DS eTool Policy package
Home-page: https://github.com/syslabcom/dsetool.policy
Author: ale-rt
Author-email: alessandro.pisa@gmail.com
License: GPL version 2
Project-URL: PyPI, https://pypi.python.org/pypi/dsetool.policy
Project-URL: Source, https://github.com/syslabcom/dsetool.policy
Project-URL: Tracker, https://github.com/syslabcom/dsetool.policy/issues
Keywords: Python Plone CMS
Classifier: Environment :: Web Environment
Classifier: Framework :: Plone
Classifier: Framework :: Plone :: Addon
Classifier: Framework :: Plone :: 5.2
Classifier: Programming Language :: Python
Classifier: Programming Language :: Python :: 3.9
Classifier: Programming Language :: Python :: 3.10
Classifier: Programming Language :: Python :: 3.11
Classifier: Programming Language :: Python :: 3.12
Classifier: Operating System :: OS Independent
Classifier: License :: OSI Approved :: GNU General Public License v2 (GPLv2)
Requires-Dist: setuptools
Requires-Dist: osha.oira
Requires-Dist: z3c.jbot
Provides-Extra: tests
Requires-Dist: plone.app.testing; extra == "tests"
Requires-Dist: plone.app.robotframework; extra == "tests"
Dynamic: author
Dynamic: author-email
Dynamic: classifier
Dynamic: description
Dynamic: description-content-type
Dynamic: home-page
Dynamic: keywords
Dynamic: license
Dynamic: project-url
Dynamic: provides-extra
Dynamic: requires-dist
Dynamic: summary
